{
  "parent": "minecraft:recipes/root",
  "criteria": {
    "has_golden_nether_brick_slab": {
      "conditions": {
        "items": [
          {
            "items": [
              "goldelight:golden_nether_brick_slab"
            ]
          }
        ]
      },
      "trigger": "minecraft:inventory_changed"
    },
    "has_the_recipe": {
      "conditions": {
        "recipe": "goldelight:chiseled_golden_nether_bricks"
      },
      "trigger": "minecraft:recipe_unlocked"
    }
  },
  "requirements": [
    [
      "has_golden_nether_brick_slab",
      "has_the_recipe"
    ]
  ],
  "rewards": {
    "recipes": [
      "goldelight:chiseled_golden_nether_bricks"
    ]
  },
  "sends_telemetry_event": false
}